lamin_spatial/__init__.py
lamin_spatial/spatialdata_curator.py
lamin_spatial-0.1.0.dist-info/LICENSE
lamin_spatial-0.1.0.dist-info/WHEEL
lamin_spatial-0.1.0.dist-info/METADATA
lamin_spatial-0.1.0.dist-info/RECORD
